{
  "InferiusQoL.ModName": "Inferius Quality of Life",

  "InferiusQoL.Status.Header": "InferiusQoL v{0}",
  "InferiusQoL.Status.Verbosity": "Úroveň logování: {0}",
  "InferiusQoL.Status.CustomizedStorage": "CustomizedStorage detekován: {0}",
  "InferiusQoL.Status.AdvancedInventory": "AdvancedInventory detekován: {0}",
  "InferiusQoL.Status.BagEquipment": "BagEquipment detekován: {0}",
  "InferiusQoL.Status.Features": "Funkce:",
  "InferiusQoL.Status.InventoryResize": "Zvětšení inventáře:",
  "InferiusQoL.Status.LockerResize": "Zvětšení skříní:",
  "InferiusQoL.Status.Backpacks": "Batohy:",
  "InferiusQoL.Status.SeamothTurbo": "Seamoth Turbo:",
  "InferiusQoL.Status.Retriever": "Retriever:",
  "InferiusQoL.Status.Compressor": "Lis:",
  "InferiusQoL.Status.TankWelder": "Spojování lahví:",
  "InferiusQoL.Status.BatteryRework": "Rework baterií:",
  "InferiusQoL.Status.TeleportBeacon": "Teleport Beacon:",

  "InferiusQoL.Console.LogLevelCurrent": "Aktuální úroveň logu: {0}. Použití: qol_log_level <None|Info|Debug|Trace>",
  "InferiusQoL.Console.LogLevelSet": "Úroveň logu nastavena na: {0}",
  "InferiusQoL.Console.NotImplemented": "Funkce není zatím implementována: {0}",

  "InferiusQoL.On": "ZAP",
  "InferiusQoL.Off": "vyp",

  "InferiusSeamothTurboMK1": "Seamoth Turbo Modul MK1",
  "Tooltip_InferiusSeamothTurboMK1": "Základní zrychlení při sprintu. Aktivuje se podržením klávesy Sprint. Vypnuto nad hladinou. Mid-game tier.",

  "InferiusSeamothTurboMK2": "Seamoth Turbo Modul MK2",
  "Tooltip_InferiusSeamothTurboMK2": "Vylepšené turbo s vyšším rychlostním stropem a spotřebou. Craft spotřebuje MK1 modul. Late mid-game tier.",

  "InferiusSeamothTurboMK3": "Seamoth Turbo Modul MK3",
  "Tooltip_InferiusSeamothTurboMK3": "Endgame turbo s nejvyšším zrychlením a spotřebou. Craft spotřebuje MK2 modul."
}
